prompt_chorus/__init__.py
prompt_chorus/cli.py
prompt_chorus/web_server.py
prompt_chorus/core/__init__.py
prompt_chorus/core/models.py
prompt_chorus/core/storage.py
prompt_chorus/core/versioning.py
prompt_chorus/decorators/__init__.py
prompt_chorus/decorators/chorus.py
prompt_chorus/utils/__init__.py
prompt_chorus/utils/colors.py
prompt_chorus/utils/prompt_extraction.py
prompt_chorus-0.1.2.dist-info/licenses/LICENSE
prompt_chorus-0.1.2.dist-info/METADATA
prompt_chorus-0.1.2.dist-info/WHEEL
prompt_chorus-0.1.2.dist-info/entry_points.txt
prompt_chorus-0.1.2.dist-info/top_level.txt
prompt_chorus-0.1.2.dist-info/RECORD
